grepexercises/__init__.py
grepexercises/app_guide.md
grepexercises/grep_exercises.css
grepexercises/grep_exercises.py
grepexercises/questions.json
grepexercises/user_progress.json
grepexercises/sample_input/.hidden
grepexercises/sample_input/code.txt
grepexercises/sample_input/colors_1
grepexercises/sample_input/colors_2.txt
grepexercises/sample_input/lines.txt
grepexercises/sample_input/nul_separated
grepexercises/sample_input/patterns.txt
grepexercises/sample_input/pcre.txt
grepexercises/sample_input/regex_terms.txt
grepexercises/sample_input/sample.txt
grepexercises/sample_input/substitute.sh
grepexercises/sample_input/terms.txt
grepexercises/sample_input/backups/color list.txt
grepexercises/sample_input/backups/dot_files/.bash_aliases
grepexercises/sample_input/backups/dot_files/.inputrc
grepexercises/sample_input/projects/python/hello.py
grepexercises/sample_input/projects/shell/hello.sh
grepexercises-1.6.0.dist-info/METADATA
grepexercises-1.6.0.dist-info/WHEEL
grepexercises-1.6.0.dist-info/entry_points.txt
grepexercises-1.6.0.dist-info/licenses/LICENSE
grepexercises-1.6.0.dist-info/RECORD
