Metadata-Version: 2.4
Name: grepexercises
Version: 1.6.0
Summary: 50+ exercises for GNU grep (or alternatives like ripgrep)
Project-URL: Source, https://github.com/learnbyexample/TUI-apps/tree/main/GrepExercises
Project-URL: Issues, https://github.com/learnbyexample/TUI-apps/issues
Author-email: Sundeep Agarwal <learnbyexample.net@gmail.com>
License-File: LICENSE
Classifier: License :: OSI Approved :: MIT License
Classifier: Operating System :: OS Independent
Classifier: Programming Language :: Python :: 3
Requires-Python: >=3.9
Requires-Dist: textual==0.85.2
